auton_survival/__init__.py
auton_survival/datasets/framingham.csv
auton_survival/datasets/pbc2.csv
auton_survival/datasets/support2.csv
auton_survival/datasets/synthetic_dataset.csv
auton_survival/datasets.py
auton_survival/estimators.py
auton_survival/experiments.py
auton_survival/metrics.py
auton_survival/models/cmhe/__init__.py
auton_survival/models/cmhe/cmhe_torch.py
auton_survival/models/cmhe/cmhe_utilities.py
auton_survival/models/cph/__init__.py
auton_survival/models/cph/dcph_torch.py
auton_survival/models/cph/dcph_utilities.py
auton_survival/models/dcm/__init__.py
auton_survival/models/dcm/dcm_torch.py
auton_survival/models/dcm/dcm_utilities.py
auton_survival/models/dsm/__init__.py
auton_survival/models/dsm/datasets/framingham.csv
auton_survival/models/dsm/datasets/pbc2.csv
auton_survival/models/dsm/datasets/support2.csv
auton_survival/models/dsm/datasets.py
auton_survival/models/dsm/dsm_torch.py
auton_survival/models/dsm/losses.py
auton_survival/models/dsm/utilities.py
auton_survival/phenotyping.py
auton_survival/preprocessing.py
auton_survival/reporting.py
auton_survival/utils.py
auton_survival_demo-1.1.0.dist-info/LICENSE
auton_survival_demo-1.1.0.dist-info/METADATA
auton_survival_demo-1.1.0.dist-info/WHEEL
auton_survival_demo-1.1.0.dist-info/RECORD
