Metadata-Version: 2.1
Name: auton-survival-demo
Version: 1.1.0
Summary: 
Author: Chirag Nagpal
Author-email: chiragn@cs.cmu.edu
Requires-Python: >=3.8,<4.0
Classifier: Programming Language :: Python :: 3
Classifier: Programming Language :: Python :: 3.8
Classifier: Programming Language :: Python :: 3.9
Classifier: Programming Language :: Python :: 3.10
Classifier: Programming Language :: Python :: 3.11
Requires-Dist: lifelines (>=0.26,<0.27)
Requires-Dist: numpy (>=1.24,<2.0)
Requires-Dist: pandas (>=1.5,<2.0)
Requires-Dist: scikit-learn (>=1.2,<2.0)
Requires-Dist: scikit-survival (>=0.21,<0.22)
Requires-Dist: torch (>=1.13,<2.0)
Requires-Dist: torchvision (>=0.14,<0.15)
Requires-Dist: tqdm (>=4.66,<5.0)
